eea_pkg/__init__.py
eea_pkg/utils.py
zkeea_pkg/__init__.py
zkeea_pkg/utils.py
zkeea-1.0.2.dist-info/LICENSE
zkeea-1.0.2.dist-info/METADATA
zkeea-1.0.2.dist-info/WHEEL
zkeea-1.0.2.dist-info/dependency_links.txt
zkeea-1.0.2.dist-info/top_level.txt
zkeea-1.0.2.dist-info/RECORD
